{
  "book": "Habakkuk",
  "abbreviation": "Hab",
  "number": 35,
  "testament": "OT",
  "chapters": [
    {
      "chapter": 1,
      "superscription": null,
      "heading": null,
      "verses": [
        {
          "verse": 1,
          "heading": null,
          "text": "ነቢዩ ዕንባቆም የተቀበለው መልእክት፤",
          "footnotes": []
        },
        {
          "verse": 2,
          "heading": null,
          "text": "«ያህዌ ሆይ፣ ለርዳታ ወደ አንተ ስጮኽ የማትሰማው እስከ መቼ ነው? «ግፍ በዛ!» በማለት ወደ አንተ ጮኽሁ፤ አንተ ግን አላዳንኸኝም፡፡",
          "footnotes": []
        },
        {
          "verse": 3,
          "heading": null,
          "text": "ርኩሰትና በደልን ለምን እንዳይ አደረግኸኝ? ጥፋና ዐመፅ በፊቴ ናቸው፤ ፀብና ጭቅጭቅም እየበዛ ነው!",
          "footnotes": []
        },
        {
          "verse": 4,
          "heading": null,
          "text": "ስለዚህ ሕግ ላልቶአል፤ ፍትሕ ተዛብቶአል፡፡ ክፉዎች ጻድቃንን ከብበዋል ስለዚህ ፍርድ ተጣሟል፡፡» ያህዌ እንዲህ በማለት ለዕንባቆም መለሰ",
          "footnotes": []
        },
        {
          "verse": 5,
          "heading": null,
          "text": "«ቢነገራችሁ እንኳ የማታምኑትን አንድ ነገር በዘመናችሁ ስለማደርግ፣ ልብ አድርጋችሁ አሕዛብን እዩ፤ ተመልከቱ፤ እጅግም ተደነቁ፡፡",
          "footnotes": []
        },
        {
          "verse": 6,
          "heading": null,
          "text": "ጨካኞቹንና ችኩሎቹን ከለዳውያንን ላስነሣ ነው፤ የራሳቸው ያልሆኑ ቤቶችን ለመውሰድ በምድሪቱ ስፋትና ርዝመት ይገሠግሣሉ፡፡",
          "footnotes": []
        },
        {
          "verse": 7,
          "heading": null,
          "text": "እነርሱ አስፈሪና አስደንጋጭ ናቸው፤ ፍርዳቸውና ክብራቸው ከራሳቸው ይወጣል፡፡",
          "footnotes": []
        },
        {
          "verse": 8,
          "heading": null,
          "text": "ፈረሶቻቸው ከነብር ይልቅ ፈጣኖች፣ ከማታም ተኩላ ይልቅ፣ አስፈሪዎች ናቸው፡፡ ፈረሶቻቸው በፍጥነት ይጋልባሉ፤ ነጥቆ ለመብላት እንደሚቸኩል ንስር ፈረሰኞቻቸው ከሩቅ ይመጣሉ፡፡",
          "footnotes": []
        },
        {
          "verse": 9,
          "heading": null,
          "text": "ሁሉም ለዐመፅ ሥራ ይመጣሉ፤ ሰራዊታቸው እንደ ምድረ በዳ ነፋስ ይገሠግሣል፤ ምርኮኞችንም እንደ አሸዋ ይሰበስባል፡፡",
          "footnotes": []
        },
        {
          "verse": 10,
          "heading": null,
          "text": "ነገሥታት ላይ ይሳለቃሉ፤ ገዥዎች ላይ ያፌዛሉ፡፡ በምሽጐች ላይ በመሳቅ ዐፈር ቆልለው ይይዟቸዋል፡፡",
          "footnotes": []
        },
        {
          "verse": 11,
          "heading": null,
          "text": "ከዚያም እንደ ነፋስ አልፈው ይሄዳሉ፤ ጉልበታቸውን አምላካቸው ያደረጉ እነዚያን በደለኞች ይጠራርጋቸዋል፡፡ ዕንባቆም ለያህዌ ያቀረበው ሌላው ጥያቄ",
          "footnotes": []
        },
        {
          "verse": 12,
          "heading": null,
          "text": "አንተ የእኔ አምላክ፣ የእኔ ቅዱስ፣ አንተ ከዘላለም ጀምሮ ያለህ አይደለህምን? እኛ አንሞትም፡፡ እንዲፈርዱ ያህዌ ሾሟቸዋል፤ አንተ ዐለት ሆይ፣ ይቀጡ ዘንድ ሥልጣን ሰጠሃቸው፡፡",
          "footnotes": []
        },
        {
          "verse": 13,
          "heading": null,
          "text": "ዐይኖችህ እጅግ የነጹ በመሆናቸው ክፉ ነገርን መመልከት አይሆንላቸውም፤ አንተም ክፉ ነገር ሲሠራ ዝም ብለህ አታይም፤ ታዲያ፣ እነዚያን ዐመፀኞች ለምን ዝም ብለህ ትመለከታለህ? ዐመፀኛው ከራሱ ይልቅ ጻድቅ የሆነውን ሰው ሲውጠውስ ለምን ዝም ትላለህ?",
          "footnotes": []
        },
        {
          "verse": 14,
          "heading": null,
          "text": "ሰዎችን ባሕር ውስጥ እንዳለ ዓሣ፣ መሪ እንደሌላቸው በደረታቸው እየተሳቡ እንደሚሄዱ ፍጥረታት የምታደርጋቸው ለምንድነው?",
          "footnotes": []
        },
        {
          "verse": 15,
          "heading": null,
          "text": "ዓሣ በመንጠቆ እንደሚያዝ ሁሉንም በመንጠቆ ይይዟቸዋል፤ ሰዎችን በመረቦቻቸው ይዘው ይሰበሰቧቸዋል፡፡ ደስ የሚሰኙትና ሐሤት የሚያደርጉት ከዚህ የተነሣ ነው፡፡",
          "footnotes": []
        },
        {
          "verse": 16,
          "heading": null,
          "text": "የስቡ እንስሳት ድርሻዎቻቸው፣ የጣፈጠውም ሥጋ ምግባቸው ሆናልና ስለዚህ ለመረቦቻቸው ይሠዋሉ፤ ለአሸክላዎቻቸውም ያጥናሉ፡፡",
          "footnotes": []
        },
        {
          "verse": 17,
          "heading": null,
          "text": "ታዲያ፣ መረቦቻቸውን ባዶ እያደረጉ፣ ያለ አንዳች ርኅራኄ ሕዝቦችን መግደል መቀጠል አለባቸውን?»",
          "footnotes": []
        }
      ]
    },
    {
      "chapter": 2,
      "superscription": null,
      "heading": null,
      "verses": [
        {
          "verse": 1,
          "heading": null,
          "text": "በጥበቃ ቦታዬ እቆማለሁ፤ በመጠበቂያው ግንብ ላይ ቦታዬን እይዛለሁ፤ ምን እንደሚለኝና ለጥያቄዬ ምን መልስ እንደሚሰጥ እጠባበቃለሁ፡፡",
          "footnotes": []
        },
        {
          "verse": 2,
          "heading": null,
          "text": "ያህዌ እንዲህ በማለት መለሰልኝ፤ «ይህን ራእይ ጻፈው፤ በቀላሉ እንዲነበብ አድርገህም በጽላት ቅረጸው፡፡",
          "footnotes": []
        },
        {
          "verse": 3,
          "heading": null,
          "text": "ራእዩ የሚናገረው ገና ወደ ፊት ስለሚሆነው ነው፡፡ በመጨረሻም ይፈጸማል እንጂ፣ በፍጹም አይዋሽም፡፡",
          "footnotes": []
        },
        {
          "verse": 4,
          "heading": null,
          "text": "ተመልከት! ጠማማ ሐሳብ ያለው ሰው ታብዮአል፡፡ ጻድቁ ግን በእምነቱ ይኖራል፡፡",
          "footnotes": []
        },
        {
          "verse": 5,
          "heading": null,
          "text": "ዐርፎ እንዳይቀመጥ ወይን ጠጅ ዕብሪተኛውን ወጣት አስቶታል ይልቁን ምኞቱን እንደ መቃብር አስፍቶአል እንደ ሞት በቃኝ ማለትን አያውቅም፡፡ ሕዝቦችን ሁሌ ወደ ራሱ ይሰበስባል ሰዎችንም ሁሉ ማርኮ ይወስዳል፡፡",
          "footnotes": []
        },
        {
          "verse": 6,
          "heading": null,
          "text": "ታዲያ፣ በእንዲህ ዐይነቱ ሰው ላይ በማፌዝና በመዘባበት እንዲህ እያሉ ሁሉም አይሣለቁበትምን? ‹የተሰረቀውን ለራሱ ለሚያከማች፣ ራሱን በዐመፅ ባለጠጋ ለሚያደርግ ወዮለት! ይህ የሚቀጥለውስ እስከ መቼ ነው?",
          "footnotes": []
        },
        {
          "verse": 7,
          "heading": null,
          "text": "በአንተ የተመረሩ ድንገት አይነሡብህምን፣ አንተን የማያስደነግጡስ አይነቁብህምን? በእጃቸውም ትወድቃለህ፡፡",
          "footnotes": []
        },
        {
          "verse": 8,
          "heading": null,
          "text": "አንተ ብዙ ሕዝብ ስለ ዘረፍህ የተረፉት ሕዝቦች ይዘርፉሃል፡፡ የሰው ደም አፍስሰሃል አገሮች፣ ከተሞችና የሚኖሩባቸው ሰዎች ሁሉ ላይ ግፍ ሠርተሃል፡፡",
          "footnotes": []
        },
        {
          "verse": 9,
          "heading": null,
          "text": "በማጭበርበር በተገኘ ሀብት ቤቱን ለሚገነባ ከክፉ ለማምለጥ ቤቱን በከፍታ ላይ ለሚሠራ ወዮለት!",
          "footnotes": []
        },
        {
          "verse": 10,
          "heading": null,
          "text": "ብዙ ሰዎችን ለማጥፋት ደባ ፈጽመሃል በገዛ ቤትህ ላይ ውርደትን፣ በራስህም ላይ ኃጢአትን አድርገሃል፡፡",
          "footnotes": []
        },
        {
          "verse": 11,
          "heading": null,
          "text": "ድንጋዮች በቅጥሩ ውስጥ ይጮኻሉ፣ ከዕንጨት የተሠሩ ተሸካሚዎችም እንዲህ በማለት ይመልሱላቸዋል፣",
          "footnotes": []
        },
        {
          "verse": 12,
          "heading": null,
          "text": "«ደም በማፍሰስ ከተማን ለሚሠራ፣ በወንጀልም አገርን ለሚመሠርት ወዮለት!»",
          "footnotes": []
        },
        {
          "verse": 13,
          "heading": null,
          "text": "ሰዎች ለእሳት ማገዶ እንዲሆን እንዲለፉ፣ ሕዝቦችም በከንቱ እንደደከሙ፣ የሰራዊት ጌታ ያህዌ ወስኖ የለምን?",
          "footnotes": []
        },
        {
          "verse": 14,
          "heading": null,
          "text": "ያም ሆኖ፣ ውሃ ባሕርን እንደሚሞላ ሁሉ ምድርም የያህዌን ክብር በማወቅ ትሞላለች፡፡",
          "footnotes": []
        },
        {
          "verse": 15,
          "heading": null,
          "text": "ኅፍረተ ሥጋቸውን ለማየት ባልንጀሮቹን ለሚያጠጣ፣ እስኪሰክሩም ድረስ ወይን ለሚያቀርብላቸው ወዮለት!»",
          "footnotes": []
        },
        {
          "verse": 16,
          "heading": null,
          "text": "በክብር ፈንታ ውርደት ትሞላለህ፤ አሁን ተራው የአንተ ነውና ጠጣ፤ ኀፍረተ ሥጋህም ይገለጥ፤ በያህዌ ቀኝ እጅ ያለው ጽዋ በተራው ይመልስብሃል ክብርህን ውርደት ይሸፍነዋል፡፡",
          "footnotes": []
        },
        {
          "verse": 17,
          "heading": null,
          "text": "ሊባኖስ ላይ ያሠራኸው ግፍ ያጥለቀልቅሃል፤ እንስሶች ላይ የፈጸምኸው ጥፋት ያስደነግጥሃል፡፡ የሰው ደም አፍስሰሃል፤ አገሮች፣ ከተሞችና የሚኖሩባቸው ሰዎች ሁሉ ላይ ግፍ ሠርተሃል፡፡",
          "footnotes": []
        },
        {
          "verse": 18,
          "heading": null,
          "text": "ታዲያ፣ የቀረጽኸው ምስል ምን ይጠቅምሃል? ምስሉን የቀረጸው፣ ከቀለጠ ብረት ጣዖት የሠራ ሰው የሐሰት መምህር ነው፤ እነዚያን የማይናገሩ አማልክት ሲሠራ በገዛ እጅ ሥራው ተማምኖአልና፡፡",
          "footnotes": []
        },
        {
          "verse": 19,
          "heading": null,
          "text": "ዕንጨቱን ንቃ! ሕይወት የሌለውንም ድንጋይ ተነሣ ለሚል ወዮለት ለመሆኑ፣ እነዚህ ነገሮች ማስተማር ይችላሉን? በወርቅና በብር ተለብጦአል፤ እስትንፋስ ግን የለውም፡፡",
          "footnotes": []
        },
        {
          "verse": 20,
          "heading": null,
          "text": "ያህዌ ግን በተቀደሰ መቅደሱ አለ፤ ምድር ሁሉ በፊቱ ጸጥ ትበል!»",
          "footnotes": []
        }
      ]
    },
    {
      "chapter": 3,
      "superscription": null,
      "heading": null,
      "verses": [
        {
          "verse": 1,
          "heading": null,
          "text": "የነቢዩ ዕንባቆም ጸሎት",
          "footnotes": []
        },
        {
          "verse": 2,
          "heading": null,
          "text": "ያህዌ ሆይ፣ ስላደረግኸው ድንቅ ሥራ ሰዎች ፈራሁ፤ የቀድሞ ዘመን ሥራህን በዚህ ዘመንም አድርግ፤ በየዘመናቱም እንዲታወቅ አድርግ፡፡ በቁጣህ ውስጥ እንኳ ምሕረት ርኅራኄኅን አስብ፡፡",
          "footnotes": []
        },
        {
          "verse": 3,
          "heading": null,
          "text": "እግዚአብሔር ከቴማን፣ ቅዱሱንም ከፋራን ተራራ መጣ! ሴላ፡፡ ክብሩ ሰማያትን ሸፈነ፤ ምድር በምስጋናው ተሞላች፡፡",
          "footnotes": []
        },
        {
          "verse": 4,
          "heading": null,
          "text": "ኃይሉ ከተሰወረበት እጁ የወጡ ሁለት ጨረሮች እንደ መብረቅ ደምቀዋል፡፡",
          "footnotes": []
        },
        {
          "verse": 5,
          "heading": null,
          "text": "መቅሠፍት በፊቱ ሄደ፤ ቸነፈርም እግር በእግር ተከተለው፡፡",
          "footnotes": []
        },
        {
          "verse": 6,
          "heading": null,
          "text": "እርሱ ሲቆም ምድር ትናወጣለች፤ እርሱ ሲመለከት ሕዝቦች ይንቀጠቀጣሉ፡፡ የዘላለም ተራሮች እንኳ ተፈረካከሱ የጥንት ኮረብቶችም ዝቅ አሉ፡፡ መንገዱ ዘላለማዊ ነው፡፡",
          "footnotes": []
        },
        {
          "verse": 7,
          "heading": null,
          "text": "የኢትዮጵያ ድንኳኖች ሲጨነቁ፣ የምድያምም መኖሪያዎች ሲታወኩ አየሁ፡፡",
          "footnotes": []
        },
        {
          "verse": 8,
          "heading": null,
          "text": "ያህዌ ወንዞች ላይ ተቆጥቷልን? መዓትህስ በምንጮች ላይ ነበርን? ወይስ በፈረሶችህና በድል አድራጊ ሰረገሎችህ በጋለብህ ጊዜ ባሕር ላይ ተቆጥተህ ነበርን?",
          "footnotes": []
        },
        {
          "verse": 9,
          "heading": null,
          "text": "ቀስትህን ከሰገባው አወጣህ፤ ፍላጻህንም ለመወርወር አዘጋጀህ፡፡ ሴላ፡፡ ምድርን በወንዞች ከፈልህ፡፡",
          "footnotes": []
        },
        {
          "verse": 10,
          "heading": null,
          "text": "ተራሮች አዩህ፤ በፍርሃትም ተጨማደዱ የውሃ ወጀብ በላያቸው አለፈ፤ ጥልቁ ባሕር ድምፁን አሰማ ማዕበሉም ወደ ላይ ከፍ ከፍ አለ፡፡",
          "footnotes": []
        },
        {
          "verse": 11,
          "heading": null,
          "text": "ከሚወረወሩ ፍላጾች ብርሃን፣ ከሚያብረቀርቀው የጦርህ ነጸብራቅ የተነሣ ፀሐይና ጨረቃ በቦታቸው ቆሙ፡፡",
          "footnotes": []
        },
        {
          "verse": 12,
          "heading": null,
          "text": "በቁጣህ በምድር ላይ ተመላለስህ፤ በመዓትህ ሕዝቦችን አደቀቅህ፡፡",
          "footnotes": []
        },
        {
          "verse": 13,
          "heading": null,
          "text": "ሕዝብህን ለማዳን፣ የቀባኸውንም ለመታደግ ወጣህ፡፡ ዕርቃኑን ታስቀረው ዘንድ የዐመፃን ቤት ራስ ቀጠቀጥህ፡፡ ሴላ፡፡",
          "footnotes": []
        },
        {
          "verse": 14,
          "heading": null,
          "text": "እንደ ዐውሎ ነፋስ ሊበታትን የመጣውን፣ ምስኪኑን በስውር ለመዋጥ የመጣውን ሰራዊት አለቃ ራስ በገዛ ፍላጻው ወጋህ፡፡",
          "footnotes": []
        },
        {
          "verse": 15,
          "heading": null,
          "text": "በፈረሶችህ ባሕሩ ላይ ተራመድህ፤ ታላላቅ ውሆችን ከመርህ፡፡",
          "footnotes": []
        },
        {
          "verse": 16,
          "heading": null,
          "text": "እኔ ሰማሁ ውስጤም ተናወጠ፤ ከድምፁ የተነሣ ከንፈሮቼ ተንቀጠቀጡ፡፡ አጥንቶቼ ይበሰብሳሉ፤ እግሮቼም ከታች ይርዳሉ ወራሪዎቻችን ላይ መከራ የሚመጣበትን ቀን በትዕግሥት እጠብቃለሁ፡፡",
          "footnotes": []
        },
        {
          "verse": 17,
          "heading": null,
          "text": "ምንም እንኳ የበለስ ዛፍ ባያብብ፣ ወይን ዛፍ ላይ ፍሬ ባይገኝ፣ የወይራ ዛፍ ምንም ፍሬ ባይሰጥ፣ ከእርሻዎች ሰብል ቢጠፋ፣ የበግ መንጋዎች ሁሉ ቢያልቁ፣ በረት ውስጥ ምንም ከብት ባይገኝ፣",
          "footnotes": []
        },
        {
          "verse": 18,
          "heading": null,
          "text": "ይህም ሁሉ ቢሆን፣ እኔ በያህዌ ደስ ይለኛል በመድኃኒቴም አምላክ ሐሤት አደርጋለሁ፡፡",
          "footnotes": []
        },
        {
          "verse": 19,
          "heading": null,
          "text": "ጌታ ያህዌ ኃይሌ ነው፤ እግሮቼን እንደ ዋሊያ እግሮች ያደርጋል፤ በከፍታዎቼም ላይ ይመራኛል፡፡ - ለመዘምራን አለቃ በባለ አውታር መሣሪያዎች የተዘመረ፡፡",
          "footnotes": []
        }
      ]
    }
  ]
}