{
  "book": "Titus",
  "abbreviation": "Titus",
  "number": 56,
  "testament": "NT",
  "chapters": [
    {
      "chapter": 1,
      "superscription": null,
      "heading": null,
      "verses": [
        {
          "verse": 1,
          "heading": null,
          "text": "Pál, Istennek szolgája, Jézus Krisztusnak pedig apostola, az Isten választottainak hite és a kegyesség szerint való igazságnak megismerése szerint,",
          "footnotes": []
        },
        {
          "verse": 2,
          "heading": null,
          "text": "Az örök élet reménységére, melyet megígért az igazmondó Isten örök időknek előtte,",
          "footnotes": []
        },
        {
          "verse": 3,
          "heading": null,
          "text": "Megjelentette pedig a maga idejében az ő beszédét a prédikálás által, a mely reám bízatott a mi megtartó Istenünknek parancsolata szerint; Titusnak, a közös hit szerint való igaz fiamnak:",
          "footnotes": []
        },
        {
          "verse": 4,
          "heading": null,
          "text": "Kegyelem, irgalmasság és békesség az Atya Istentől és az Úr Jézus Krisztustól, a mi Megtartónktól.",
          "footnotes": []
        },
        {
          "verse": 5,
          "heading": null,
          "text": "A végett hagytalak téged Krétában, hogy a hátramaradt dolgokat hozd rendbe, és rendelj városonként presbitereket, a miképen én néked meghagytam;",
          "footnotes": []
        },
        {
          "verse": 6,
          "heading": null,
          "text": "Ha van feddhetetlen, egy feleségű férfiú, a kinek hívő, nem kicsapongással vádolt avagy engedetlen gyermekei vannak.",
          "footnotes": []
        },
        {
          "verse": 7,
          "heading": null,
          "text": "Mert szükséges, hogy a püspök feddhetetlen legyen, mint Isten sáfára; nem akaratos, nem haragos, nem részeges, nem verekedő, nem rút nyerészkedő;",
          "footnotes": []
        },
        {
          "verse": 8,
          "heading": null,
          "text": "Hanem vendégszerető, jónak kedvelője, mértékletes, igaz, tiszta, maga tűrtető;",
          "footnotes": []
        },
        {
          "verse": 9,
          "heading": null,
          "text": "A ki a tudomány szerint való igaz beszédhez tartja magát, hogy inthessen az egészséges tudománnyal és meggyőzhesse az ellenkezőket.",
          "footnotes": []
        },
        {
          "verse": 10,
          "heading": null,
          "text": "Mert van sok engedetlen, hiába való beszédű és csaló, kiváltképen a körülmetélkedésből valók,",
          "footnotes": []
        },
        {
          "verse": 11,
          "heading": null,
          "text": "A kiknek be kell dugni a szájokat; a kik egész házakat feldúlnak, tanítván rút nyereség okáért, a miket nem kellene.",
          "footnotes": []
        },
        {
          "verse": 12,
          "heading": null,
          "text": "Azt mondta valaki közülök, az ő saját prófétájok: A krétaiak mindig hazugok, gonosz vadak, rest hasak.",
          "footnotes": []
        },
        {
          "verse": 13,
          "heading": null,
          "text": "E bizonyság igaz: annakokáért fedd őket kímélés nélkül, hogy a hitben épek legyenek,",
          "footnotes": []
        },
        {
          "verse": 14,
          "heading": null,
          "text": "Nem ügyelvén zsidó mesékre, és az igazságot megvető emberek parancsolataira.",
          "footnotes": []
        },
        {
          "verse": 15,
          "heading": null,
          "text": "Minden tiszta a tisztáknak: de a megfertőztetetteknek és hitetleneknek semmi sem tiszta; hanem megfertőztetett azoknak mind elméjök, mind lelkiismeretök.",
          "footnotes": []
        },
        {
          "verse": 16,
          "heading": null,
          "text": "Vallják, hogy Istent ismerik, de cselekedeteikkel tagadják, mivelhogy útálatosak és hitetlenek és minden jó cselekedetre méltatlanok.",
          "footnotes": []
        }
      ]
    },
    {
      "chapter": 2,
      "superscription": null,
      "heading": null,
      "verses": [
        {
          "verse": 1,
          "heading": null,
          "text": "Te pedig azokat szóljad, a mik az egészséges tudományhoz illenek.",
          "footnotes": []
        },
        {
          "verse": 2,
          "heading": null,
          "text": "Hogy a vén emberek józanok legyenek, tisztességesek, mértékletesek; a hitben, szeretetben, tűrésben épek.",
          "footnotes": []
        },
        {
          "verse": 3,
          "heading": null,
          "text": "Hasonlóképen a vén asszonyok szentekhez illő magaviseletűek legyenek, nem patvarkodók, sem sok borivás rabjai, jóra oktatók;",
          "footnotes": []
        },
        {
          "verse": 4,
          "heading": null,
          "text": "Hogy megokosítsák az ifjú asszonyokat, hogy férjöket és magzataikat szeressék,",
          "footnotes": []
        },
        {
          "verse": 5,
          "heading": null,
          "text": "Legyenek mértékletesek, tiszták, háziasak, jók, férjöknek engedelmesek, hogy az Isten beszéde ne káromoltassék.",
          "footnotes": []
        },
        {
          "verse": 6,
          "heading": null,
          "text": "Az ifjakat hasonlóképen intsed, hogy legyenek mértékletesek:",
          "footnotes": []
        },
        {
          "verse": 7,
          "heading": null,
          "text": "Mindenben tenmagadat adván példaképül a jó cselekedetekben; a tudományban romlatlanságot, méltóságot mutatván,",
          "footnotes": []
        },
        {
          "verse": 8,
          "heading": null,
          "text": "Egészséges, feddhetetlen beszédet; hogy az ellenfél megszégyenüljön, semmi gonoszt sem tudván rólatok mondani.",
          "footnotes": []
        },
        {
          "verse": 9,
          "heading": null,
          "text": "A szolgákat intsed, hogy az ő uraiknak engedelmeskedjenek, mindenben kedvöket keressék, ne ellenkezzenek,",
          "footnotes": []
        },
        {
          "verse": 10,
          "heading": null,
          "text": "Ne tolvajkodjanak, hanem teljes jó hűséget tanusítsanak; hogy a mi megtartó Istenünknek tudományát ékesítsék mindenben.",
          "footnotes": []
        },
        {
          "verse": 11,
          "heading": null,
          "text": "Mert megjelent az Isten idvezítő kegyelme minden embernek,",
          "footnotes": []
        },
        {
          "verse": 12,
          "heading": null,
          "text": "A mely arra tanít minket, hogy megtagadván a hitetlenséget és a világi kivánságokat, mértékletesen, igazán és szentül éljünk a jelenvaló világon:",
          "footnotes": []
        },
        {
          "verse": 13,
          "heading": null,
          "text": "Várván ama boldog reménységet és a nagy Istennek és megtartó Jézus Krisztusunknak dicsősége megjelenését;",
          "footnotes": []
        },
        {
          "verse": 14,
          "heading": null,
          "text": "A ki önmagát adta mi érettünk, hogy megváltson minket minden hamisságtól, és tisztítson önmagának kiváltképen való népet, jó cselekedetekre igyekezőt.",
          "footnotes": []
        },
        {
          "verse": 15,
          "heading": null,
          "text": "Ezeket szóljad, és ints és feddj teljes méltósággal; senki téged meg ne vessen.",
          "footnotes": []
        }
      ]
    },
    {
      "chapter": 3,
      "superscription": null,
      "heading": null,
      "verses": [
        {
          "verse": 1,
          "heading": null,
          "text": "Emlékeztessed őket, hogy a fejedelemségeknek és hatalmasságoknak engedelmeskedjenek, hódoljanak, minden jó cselekedetre készek legyenek,",
          "footnotes": []
        },
        {
          "verse": 2,
          "heading": null,
          "text": "Senkit ne szidalmazzanak, ne veszekedjenek, gyöngédek legyenek, teljes szelídséget tanusítván minden ember iránt.",
          "footnotes": []
        },
        {
          "verse": 3,
          "heading": null,
          "text": "Mert régenten mi is esztelenek, engedetlenek, tévelygők, különböző kívánságoknak és gyönyöröknek szolgái, gonoszságban és irígységben élők, gyűlölségesek, egymást gyűlölők valánk.",
          "footnotes": []
        },
        {
          "verse": 4,
          "heading": null,
          "text": "De mikor a mi megtartó Istenünknek jóvolta és az emberekhez való szeretete megjelent,",
          "footnotes": []
        },
        {
          "verse": 5,
          "heading": null,
          "text": "Nem az igazságnak cselekedeteiből, a melyeket mi cselekedtünk, hanem az ő irgalmasságából tartott meg minket az újjászületésnek fürdője és a Szent Lélek megújítása által,",
          "footnotes": []
        },
        {
          "verse": 6,
          "heading": null,
          "text": "Melyet kitöltött reánk bőséggel a mi megtartó Jézus Krisztusunk által;",
          "footnotes": []
        },
        {
          "verse": 7,
          "heading": null,
          "text": "Hogy az ő kegyelméből megigazulván, örökösök legyünk az örök élet reménysége szerint.",
          "footnotes": []
        },
        {
          "verse": 8,
          "heading": null,
          "text": "Igaz ez a beszéd, és akarom, hogy ezeket erősítsed, hogy igyekezzenek jó cselekedetekkel előljárni azok, a kik Istenben hívőkké lettek. Ezek jók és hasznosak az embereknek;",
          "footnotes": []
        },
        {
          "verse": 9,
          "heading": null,
          "text": "A balgatag vitatkozásokat azonban és a nemzetségekről való tudakozásokat, és a civakodást és a törvény felől való harczokat kerüld; mert haszontalanok és hiábavalók.",
          "footnotes": []
        },
        {
          "verse": 10,
          "heading": null,
          "text": "Az eretnek embert egy vagy két intés után kerüld;",
          "footnotes": []
        },
        {
          "verse": 11,
          "heading": null,
          "text": "Tudván, hogy az ilyen romlott, és vétkezik, önmaga is kárhoztatván magát.",
          "footnotes": []
        },
        {
          "verse": 12,
          "heading": null,
          "text": "Mikor Ártemást vagy Tikhikust hozzád küldöm, siess hozzám jőni Nikápolyba; mert elhatároztam, hogy ott töltöm a telet.",
          "footnotes": []
        },
        {
          "verse": 13,
          "heading": null,
          "text": "A törvénytudó Zénást és Apollóst gondosan indítsd útnak, hogy semmiben se legyen fogyatkozásuk.",
          "footnotes": []
        },
        {
          "verse": 14,
          "heading": null,
          "text": "Tanulják meg pedig a mieink is, hogy jó cselekedetekkel járjanak elől a szükséges hasznokra, hogy ne legyenek gyümölcstelenek.",
          "footnotes": []
        },
        {
          "verse": 15,
          "heading": null,
          "text": "Köszöntenek téged a velem levők mindnyájan. Köszöntsd azokat, a kik szeretnek minket hitben. Kegyelem mindnyájatokkal! Ámen.",
          "footnotes": []
        }
      ]
    }
  ]
}